LICENSE
README.md
setup.py
bsync/__ini__.py
bsync/__version__.py
bsync/api.py
bsync/cli.py
bsync/log.py
bsync/settings.py
bsync/sync.py
bsync.egg-info/PKG-INFO
bsync.egg-info/SOURCES.txt
bsync.egg-info/dependency_links.txt
bsync.egg-info/entry_points.txt
bsync.egg-info/requires.txt
bsync.egg-info/top_level.txt