Metadata-Version: 2.1
Name: bsync
Version: 1.2.0
Summary: Sync files from your computer to Box.com using the Box API. Think rsync for Box.com
Home-page: https://github.com/spacetelescope/bsync
Author: Justin Quick
Author-email: jquick@stsci.edu
License: APACHE 2
Project-URL: Documentation, https://bsync.readthedocs.io/en/latest/
Project-URL: Source, https://github.com/spacetelescope/bsync
Platform: UNKNOWN
Classifier: Development Status :: 4 - Beta
Classifier: Programming Language :: Python :: 3
Classifier: License :: OSI Approved :: BSD License
Classifier: Operating System :: OS Independent
Classifier: Environment :: Console
Requires-Python: >=3.6
